[
    {
        "_id": "63b57c04edfc7d4fccdb9a2d",
        "keywords": [
            "footbal",
            "islands",
            "timezone"
        ],
        "questions": [
            {
                "_id": "63b57c04edfc7d4fccdb9a29"
            },
            {
                "_id": "63b57c04edfc7d4fccdb9a2b"
            }
        ],
        "questionnaireID": "QQ000",
        "questionnaireTitle": "My first research questionnaire"
    },
    {
        "_id": "63b57c16edfc7d4fccdb9a4b",
        "keywords": [
            "footbal",
            "islands",
            "timezone"
        ],
        "questions": [
            {
                "_id": "63b57c15edfc7d4fccdb9a43"
            },
            {
                "_id": "63b57c16edfc7d4fccdb9a45"
            },
            {
                "_id": "63b57c16edfc7d4fccdb9a47"
            },
            {
                "_id": "63b57c16edfc7d4fccdb9a49"
            }
        ],
        "questionnaireID": "QQ001",
        "questionnaireTitle": "My second research questionnaire"
    },
    {
        "_id": "63b6f8cd945aba5410493f82",
        "keywords": [
            "footbal",
            "islands",
            "timezone"
        ],
        "questions": [
            {
                "_id": "63b6f8cc945aba5410493f7a"
            },
            {
                "_id": "63b6f8cd945aba5410493f7c"
            },
            {
                "_id": "63b6f8cd945aba5410493f7e"
            },
            {
                "_id": "63b6f8cd945aba5410493f80"
            }
        ],
        "questionnaireID": "QQ042",
        "questionnaireTitle": "My third research questionnaire"
    },
    {
        "_id": "63bc110ded7ab64f38d39687",
        "keywords": [
            "footbal",
            "islands",
            "timezone"
        ],
        "questions": [
            {
                "_id": "63bc110ded7ab64f38d3967d"
            },
            {
                "_id": "63bc110ded7ab64f38d3967f"
            },
            {
                "_id": "63bc110ded7ab64f38d39681"
            },
            {
                "_id": "63bc110ded7ab64f38d39683"
            },
            {
                "_id": "63bc110ded7ab64f38d39685"
            }
        ],
        "questionnaireID": "QQ052",
        "questionnaireTitle": "My fourth research questionnaire"
    },
    {
        "_id": "63bd62925397442ec4c12440",
        "keywords": [
            "footbal",
            "islands",
            "timezone"
        ],
        "questions": [
            {
                "_id": "63bd62915397442ec4c12436"
            },
            {
                "_id": "63bd62915397442ec4c12438"
            },
            {
                "_id": "63bd62915397442ec4c1243a"
            },
            {
                "_id": "63bd62925397442ec4c1243c"
            },
            {
                "_id": "63bd62925397442ec4c1243e"
            }
        ],
        "questionnaireID": "QQ062",
        "questionnaireTitle": "My fifth research questionnaire"
    }
]